{
  "data_game": [
    {
      "nama": "Loading Awal",
      "tanggal": "2025-07-01",
      "tanggal_awal": "2025-07-01",
      "tanggal_akhir": "2025-12-31",
      "link": "https://indianetworknews.com/wp-content/uploads/2024/03/Garena-Free-Fire-Max-Redeem-Codes-Released-for-25-March-2024.webp"
    },
    {
      "nama": "Login Banner",
      "tanggal": "2025-07-01",
      "tanggal_awal": "2025-07-01",
      "tanggal_akhir": "2025-12-31",
      "link": "https://www.loginbanner.com"
    },
    {
      "nama": "Lobby Banner",
      "tanggal": "2025-07-01",
      "tanggal_awal": "2025-07-01",
      "tanggal_akhir": "2025-12-31",
      "link": "https://www.lobbybanner.com"
    },
    {
      "nama": "Login Sound",
      "tanggal": "2025-07-01",
      "tanggal_awal": "2025-07-01",
      "tanggal_akhir": "2025-12-31",
      "link": "https://www.loginsound.com"
    },
    {
      "nama": "Lobby Sound",
      "tanggal": "2025-07-01",
      "tanggal_awal": "2025-07-01",
      "tanggal_akhir": "2025-12-31",
      "link": "https://www.lobbysound.com"
    }
  ]
}
